coolnum.py
coolnum-0.1.dist-info/entry_points.txt
coolnum-0.1.dist-info/WHEEL
coolnum-0.1.dist-info/METADATA
coolnum-0.1.dist-info/RECORD
