Metadata-Version: 2.1
Name: coolnum
Version: 0.1
Summary: 一个把百分数转化成float数的函数
Keywords: 
Author-email: jutooy <jutooy@qq.com>
Classifier: License :: OSI Approved :: Apache Software License
